profq_sorting/__init__.py
profq_sorting/helpers/__init__.py
profq_sorting/helpers/max.py
profq_sorting/sorting/__init__.py
profq_sorting/sorting/bubble_sort.py
profq_sorting/sorting/bucket_sort.py
profq_sorting/sorting/counting_sort.py
profq_sorting/sorting/insertion_sort.py
profq_sorting/sorting/merge_sort.py
profq_sorting/sorting/quick_sort.py
profq_sorting/sorting/radix_sort.py
profq_sorting/sorting/selection_sort.py
profq_sorting/sorting/shell_sort.py
profq_sorting/sorting/timsort.py
profq_sorting-1.0.1.dist-info/LICENSE
profq_sorting-1.0.1.dist-info/METADATA
profq_sorting-1.0.1.dist-info/WHEEL
profq_sorting-1.0.1.dist-info/top_level.txt
profq_sorting-1.0.1.dist-info/RECORD
